bofhexcuse/__init__.py
bofhexcuse/bofh_excuses.json
bofhexcuse-0.3.0.dist-info/DESCRIPTION.rst
bofhexcuse-0.3.0.dist-info/METADATA
bofhexcuse-0.3.0.dist-info/RECORD
bofhexcuse-0.3.0.dist-info/WHEEL
bofhexcuse-0.3.0.dist-info/entry_points.txt
bofhexcuse-0.3.0.dist-info/metadata.json
bofhexcuse-0.3.0.dist-info/top_level.txt
