Metadata-Version: 2.0
Name: bofhexcuse
Version: 0.3.0
Summary: Generate random BOFH themed technical excuses!
Home-page: https://github.com/okzach/bofhexcuse/
Author: Zach Adams
Author-email: zach@okzach.com
License: MIT
Platform: UNKNOWN
Classifier: Development Status :: 3 - Alpha
Classifier: License :: OSI Approved :: MIT License
Classifier: Natural Language :: English
Classifier: Environment :: Console
Classifier: Programming Language :: Python :: 2
Classifier: Programming Language :: Python :: 2.7
Classifier: Programming Language :: Python :: 3
Classifier: Programming Language :: Python :: 3.5
Classifier: Topic :: Games/Entertainment :: Fortune Cookies
